cube_alchemy_streamlit_components/__init__.py
cube_alchemy_streamlit_components/filter/__init__.py
cube_alchemy_streamlit_components/filter/example.py
cube_alchemy_streamlit_components/filter/frontend/build/bootstrap.min.css
cube_alchemy_streamlit_components/filter/frontend/build/index.html
cube_alchemy_streamlit_components/filter/frontend/build/assets/index-CeDkz9L5.js
cube_alchemy_streamlit_components/filter/frontend/build/assets/index-DVqrtgNf.css
cube_alchemy_streamlit_components-0.1.1.dist-info/licenses/LICENSE
cube_alchemy_streamlit_components-0.1.1.dist-info/METADATA
cube_alchemy_streamlit_components-0.1.1.dist-info/WHEEL
cube_alchemy_streamlit_components-0.1.1.dist-info/top_level.txt
cube_alchemy_streamlit_components-0.1.1.dist-info/RECORD
